paradag/VERSION
paradag/__init__.py
paradag/callable_executor.py
paradag/error.py
paradag/multi_thread_processor.py
paradag/sequential_processor.py
paradag-1.2.0.dist-info/LICENSE
paradag-1.2.0.dist-info/METADATA
paradag-1.2.0.dist-info/WHEEL
paradag-1.2.0.dist-info/top_level.txt
paradag-1.2.0.dist-info/RECORD
